youtube_transcript_mcp/__init__.py
youtube_transcript_mcp/youtube_transcript_mcp.py
youtube_transcript_mcp-0.2.1.dist-info/METADATA
youtube_transcript_mcp-0.2.1.dist-info/WHEEL
youtube_transcript_mcp-0.2.1.dist-info/entry_points.txt
youtube_transcript_mcp-0.2.1.dist-info/licenses/LICENSE
youtube_transcript_mcp-0.2.1.dist-info/RECORD
