Metadata-Version: 2.4
Name: youtube-transcript-mcp
Version: 0.2.1
Summary: MCP server for fetching YouTube transcripts
Author-email: Jeril Sebastian <seb988@gmail.com>
License-File: LICENSE
Requires-Python: >=3.10
Requires-Dist: mcp
Requires-Dist: youtube-transcript-api
